pyiptmnet/__init__.py
pyiptmnet/api.py
pyiptmnet/enums.py
pyiptmnet-0.1.8.dist-info/LICENSE.txt
pyiptmnet-0.1.8.dist-info/METADATA
pyiptmnet-0.1.8.dist-info/WHEEL
pyiptmnet-0.1.8.dist-info/top_level.txt
pyiptmnet-0.1.8.dist-info/RECORD
