Metadata-Version: 2.1
Name: pyiptmnet
Version: 0.1.8
Summary: Python client for iPTMNet REST API - https://research.bioinformatics.udel.edu/iptmnet/
Home-page: https://github.com/udel-cbcb/pyiptmnet
Download-URL: https://github.com/udel-cbcb/pyiptmnet/archive/0.1.7.tar.gz
Author: Sachn Gavali
Author-email: saching@udel.edu
License: UNKNOWN
Keywords: iPTMnet,API,Client,REST-API
Platform: UNKNOWN
License-File: LICENSE.txt
Requires-Dist: certifi
Requires-Dist: chardet
Requires-Dist: idna
Requires-Dist: jsonschema
Requires-Dist: numpy
Requires-Dist: pandas
Requires-Dist: python-dateutil
Requires-Dist: pytz
Requires-Dist: requests
Requires-Dist: six
Requires-Dist: urllib3
